README.rst
setup.py
shorter.py
shorter.egg-info/PKG-INFO
shorter.egg-info/SOURCES.txt
shorter.egg-info/dependency_links.txt
shorter.egg-info/entry_points.txt
shorter.egg-info/not-zip-safe
shorter.egg-info/requires.txt
shorter.egg-info/top_level.txt