Metadata-Version: 1.0
Name: shorter
Version: 0.1.1
Summary: Robust url shorten service with zero config.
Home-page: UNKNOWN
Author: Lx Yu
Author-email: i@lxyu.net
License: MIT
Keywords: url short shorter flask
Platform: UNKNOWN
